{
  "schema_version": 2,
  "description": "muon fake rate corrections for 2016preVFP (includes QCD systematic sources)",
  "corrections": [
    {
      "name": "fakerate_muon_Central",
      "description": "muon fake rate - Central",
      "version": 1,
      "inputs": [
        {
          "name": "absEta",
          "type": "real",
          "description": "Absolute pseudorapidity"
        },
        {
          "name": "ptCorr",
          "type": "real",
          "description": "Corrected transverse momentum [GeV]"
        }
      ],
      "output": {
        "name": "out",
        "type": "real",
        "description": "out"
      },
      "data": {
        "nodetype": "multibinning",
        "inputs": [
          "absEta",
          "ptCorr"
        ],
        "edges": [
          [
            0.0,
            0.9,
            1.6,
            2.4
          ],
          [
            10.0,
            12.0,
            14.0,
            17.0,
            20.0,
            30.0,
            50.0,
            100.0
          ]
        ],
        "content": [
          0.5170285262323375,
          0.3056628378778181,
          0.2092569407298975,
          0.17953459290670684,
          0.12389350904158361,
          0.07491821003728492,
          0.043896021216429,
          0.5244295684182034,
          0.3200739294254884,
          0.23238138639950462,
          0.19128273859642148,
          0.1452873599073025,
          0.09459622903528929,
          0.0867924467217931,
          0.5519885992334949,
          0.36724816333073357,
          0.27058739404263726,
          0.23503830573034495,
          0.1940933502602991,
          0.12305160366261038,
          0.12748251067108043
        ],
        "flow": "clamp"
      }
    },
    {
      "name": "fakerate_muon_QCD_MuEnriched",
      "description": "muon fake rate systematic - QCD_MuEnriched",
      "version": 1,
      "inputs": [
        {
          "name": "absEta",
          "type": "real",
          "description": "Absolute pseudorapidity"
        },
        {
          "name": "ptCorr",
          "type": "real",
          "description": "Corrected transverse momentum [GeV]"
        }
      ],
      "output": {
        "name": "out",
        "type": "real",
        "description": "out"
      },
      "data": {
        "nodetype": "multibinning",
        "inputs": [
          "absEta",
          "ptCorr"
        ],
        "edges": [
          [
            0.0,
            0.9,
            1.6,
            2.4
          ],
          [
            10.0,
            12.0,
            14.0,
            17.0,
            20.0,
            30.0,
            50.0,
            100.0
          ]
        ],
        "content": [
          0.5297482753165795,
          0.32028620034653543,
          0.23538733628536374,
          0.18970450696837401,
          0.13896542222180125,
          0.07942249625360541,
          0.0578029357559164,
          0.5311056907152223,
          0.3415439184321244,
          0.2522668478744624,
          0.21219363635950736,
          0.1654472324396508,
          0.10034943782631087,
          0.0722903410251676,
          0.5541009899000835,
          0.3816746392187443,
          0.2926903878379126,
          0.24538001570734486,
          0.2045757810589563,
          0.1371652957218749,
          0.10789910878298876
        ],
        "flow": "clamp"
      }
    }
  ]
}