{
  "schema_version": 2,
  "description": "Measured efficiency for Mu8El23_El23Leg Trigger path",
  "corrections": [
    {
      "name": "Mu8El23_Data",
      "description": "",
      "version": 1,
      "inputs": [
        {
          "name": "abssceta",
          "type": "real",
          "description": "abssceta"
        },
        {
          "name": "pt",
          "type": "real",
          "description": "pt"
        },
        {
          "name": "syst",
          "type": "string",
          "description": "systematic variation (nom, up, down)"
        }
      ],
      "output": {
        "name": "eff_data",
        "type": "real",
        "description": "eff_data"
      },
      "generic_formulas": null,
      "data": {
        "nodetype": "category",
        "input": "syst",
        "content": [
          {
            "key": "nom",
            "value": {
              "nodetype": "binning",
              "input": "abssceta",
              "edges": [
                0.0,
                0.800000011920929,
                1.4789999723434448,
                2.5
              ],
              "content": [
                {
                  "nodetype": "binning",
                  "input": "pt",
                  "edges": [
                    5.0,
                    10.0,
                    20.0,
                    23.0,
                    25.0,
                    30.0,
                    40.0,
                    50.0,
                    100.0,
                    200.0
                  ],
                  "content": [
                    0.0,
                    0.00030102347983142685,
                    0.08600182982616651,
                    0.8489208633093526,
                    0.9291700459583672,
                    0.9514458017627957,
                    0.9618860510805501,
                    0.9746855596242636,
                    0.989028632592989
                  ],
                  "flow": "clamp"
                },
                {
                  "nodetype": "binning",
                  "input": "pt",
                  "edges": [
                    5.0,
                    10.0,
                    20.0,
                    23.0,
                    25.0,
                    30.0,
                    40.0,
                    50.0,
                    100.0,
                    200.0
                  ],
                  "content": [
                    0.0,
                    0.001075268817204301,
                    0.09104589917231001,
                    0.716915995397008,
                    0.9253187613843351,
                    0.9517861603797152,
                    0.9600511345477788,
                    0.9712460063897763,
                    0.9787704555506413
                  ],
                  "flow": "clamp"
                },
                {
                  "nodetype": "binning",
                  "input": "pt",
                  "edges": [
                    5.0,
                    10.0,
                    20.0,
                    23.0,
                    25.0,
                    30.0,
                    40.0,
                    50.0,
                    100.0,
                    200.0
                  ],
                  "content": [
                    0.0,
                    0.001413094677343382,
                    0.03775100401606426,
                    0.39039408866995073,
                    0.8886649874055416,
                    0.9539101992268808,
                    0.963474025974026,
                    0.9717183538131461,
                    0.9799357945425361
                  ],
                  "flow": "clamp"
                }
              ],
              "flow": "clamp"
            }
          },
          {
            "key": "up",
            "value": {
              "nodetype": "binning",
              "input": "abssceta",
              "edges": [
                0.0,
                0.800000011920929,
                1.4789999723434448,
                2.5
              ],
              "content": [
                {
                  "nodetype": "binning",
                  "input": "pt",
                  "edges": [
                    5.0,
                    10.0,
                    20.0,
                    23.0,
                    25.0,
                    30.0,
                    40.0,
                    50.0,
                    100.0,
                    200.0
                  ],
                  "content": [
                    0.0,
                    0.0006564638736861108,
                    0.0925951729328518,
                    0.883425428877153,
                    0.9512074283114572,
                    0.9683904716166535,
                    0.9812775828301571,
                    0.9870645652471083,
                    1.0120087879253692
                  ],
                  "flow": "clamp"
                },
                {
                  "nodetype": "binning",
                  "input": "pt",
                  "edges": [
                    5.0,
                    10.0,
                    20.0,
                    23.0,
                    25.0,
                    30.0,
                    40.0,
                    50.0,
                    100.0,
                    200.0
                  ],
                  "content": [
                    0.0,
                    0.0023924347742536626,
                    0.10359662813873172,
                    0.7545994644876528,
                    0.9539044800546511,
                    0.9733348613890759,
                    0.9845774465215649,
                    0.9872268699742003,
                    1.008084155721052
                  ],
                  "flow": "clamp"
                },
                {
                  "nodetype": "binning",
                  "input": "pt",
                  "edges": [
                    5.0,
                    10.0,
                    20.0,
                    23.0,
                    25.0,
                    30.0,
                    40.0,
                    50.0,
                    100.0,
                    200.0
                  ],
                  "content": [
                    0.0,
                    0.002238912158442942,
                    0.043874979163821916,
                    0.41784367576156795,
                    0.9177730399309149,
                    0.9776726969278631,
                    0.991240381100007,
                    0.9910737000616685,
                    1.0194394462157959
                  ],
                  "flow": "clamp"
                }
              ],
              "flow": "clamp"
            }
          },
          {
            "key": "down",
            "value": {
              "nodetype": "binning",
              "input": "abssceta",
              "edges": [
                0.0,
                0.800000011920929,
                1.4789999723434448,
                2.5
              ],
              "content": [
                {
                  "nodetype": "binning",
                  "input": "pt",
                  "edges": [
                    5.0,
                    10.0,
                    20.0,
                    23.0,
                    25.0,
                    30.0,
                    40.0,
                    50.0,
                    100.0,
                    200.0
                  ],
                  "content": [
                    0.0,
                    -5.441691402325704e-05,
                    0.07940848671948122,
                    0.8144162977415521,
                    0.9071326636052771,
                    0.9345011319089379,
                    0.9424945193309432,
                    0.962306554001419,
                    0.9660484772606088
                  ],
                  "flow": "clamp"
                },
                {
                  "nodetype": "binning",
                  "input": "pt",
                  "edges": [
                    5.0,
                    10.0,
                    20.0,
                    23.0,
                    25.0,
                    30.0,
                    40.0,
                    50.0,
                    100.0,
                    200.0
                  ],
                  "content": [
                    0.0,
                    -0.0002418971398450607,
                    0.07849517020588831,
                    0.6792325263063632,
                    0.8967330427140191,
                    0.9302374593703545,
                    0.9355248225739927,
                    0.9552651428053524,
                    0.9494567553802308
                  ],
                  "flow": "clamp"
                },
                {
                  "nodetype": "binning",
                  "input": "pt",
                  "edges": [
                    5.0,
                    10.0,
                    20.0,
                    23.0,
                    25.0,
                    30.0,
                    40.0,
                    50.0,
                    100.0,
                    200.0
                  ],
                  "content": [
                    0.0,
                    0.000587277196243822,
                    0.0316270288683066,
                    0.3629445015783335,
                    0.8595569348801683,
                    0.9301477015258985,
                    0.935707670848045,
                    0.9523630075646237,
                    0.9404321428692762
                  ],
                  "flow": "clamp"
                }
              ],
              "flow": "clamp"
            }
          }
        ],
        "default": null
      }
    },
    {
      "name": "Mu8El23_MC",
      "description": "",
      "version": 1,
      "inputs": [
        {
          "name": "abssceta",
          "type": "real",
          "description": "abssceta"
        },
        {
          "name": "pt",
          "type": "real",
          "description": "pt"
        },
        {
          "name": "syst",
          "type": "string",
          "description": "systematic variation (nom, up, down)"
        }
      ],
      "output": {
        "name": "eff_mc",
        "type": "real",
        "description": "eff_mc"
      },
      "generic_formulas": null,
      "data": {
        "nodetype": "category",
        "input": "syst",
        "content": [
          {
            "key": "nom",
            "value": {
              "nodetype": "binning",
              "input": "abssceta",
              "edges": [
                0.0,
                0.800000011920929,
                1.4789999723434448,
                2.5
              ],
              "content": [
                {
                  "nodetype": "binning",
                  "input": "pt",
                  "edges": [
                    5.0,
                    10.0,
                    20.0,
                    23.0,
                    25.0,
                    30.0,
                    40.0,
                    50.0,
                    100.0,
                    200.0
                  ],
                  "content": [
                    0.0,
                    0.00047897497635772656,
                    0.05591841376773984,
                    0.7892396011891395,
                    0.934680489047064,
                    0.9566168840224174,
                    0.9686226857238891,
                    0.9821547515096973,
                    0.9917539165379861
                  ],
                  "flow": "clamp"
                },
                {
                  "nodetype": "binning",
                  "input": "pt",
                  "edges": [
                    5.0,
                    10.0,
                    20.0,
                    23.0,
                    25.0,
                    30.0,
                    40.0,
                    50.0,
                    100.0,
                    200.0
                  ],
                  "content": [
                    0.0,
                    0.0008176191886327371,
                    0.07112416208005307,
                    0.726564638312611,
                    0.9328942589454476,
                    0.9609612412443919,
                    0.9687786088036324,
                    0.977099157665227,
                    0.9889853435696246
                  ],
                  "flow": "clamp"
                },
                {
                  "nodetype": "binning",
                  "input": "pt",
                  "edges": [
                    5.0,
                    10.0,
                    20.0,
                    23.0,
                    25.0,
                    30.0,
                    40.0,
                    50.0,
                    100.0,
                    200.0
                  ],
                  "content": [
                    0.0,
                    0.0027805881469991265,
                    0.08609707575670937,
                    0.6283196705713671,
                    0.9305838231152783,
                    0.959641140081024,
                    0.9734453475639309,
                    0.9828679584853657,
                    0.9895250775210661
                  ],
                  "flow": "clamp"
                }
              ],
              "flow": "clamp"
            }
          },
          {
            "key": "up",
            "value": {
              "nodetype": "binning",
              "input": "abssceta",
              "edges": [
                0.0,
                0.800000011920929,
                1.4789999723434448,
                2.5
              ],
              "content": [
                {
                  "nodetype": "binning",
                  "input": "pt",
                  "edges": [
                    5.0,
                    10.0,
                    20.0,
                    23.0,
                    25.0,
                    30.0,
                    40.0,
                    50.0,
                    100.0,
                    200.0
                  ],
                  "content": [
                    0.0,
                    0.0009701827139492448,
                    0.06379275956402278,
                    0.8053943508527397,
                    0.9423458817289985,
                    0.9612542107681468,
                    0.9875427302106323,
                    0.9988628880676941,
                    1.0012532066911952
                  ],
                  "flow": "clamp"
                },
                {
                  "nodetype": "binning",
                  "input": "pt",
                  "edges": [
                    5.0,
                    10.0,
                    20.0,
                    23.0,
                    25.0,
                    30.0,
                    40.0,
                    50.0,
                    100.0,
                    200.0
                  ],
                  "content": [
                    0.0,
                    0.0038491499710415905,
                    0.07854822723044959,
                    0.7485061063022291,
                    0.9406761265776643,
                    0.9701791255367974,
                    0.979509411713211,
                    0.9870281796818697,
                    1.0016926808120163
                  ],
                  "flow": "clamp"
                },
                {
                  "nodetype": "binning",
                  "input": "pt",
                  "edges": [
                    5.0,
                    10.0,
                    20.0,
                    23.0,
                    25.0,
                    30.0,
                    40.0,
                    50.0,
                    100.0,
                    200.0
                  ],
                  "content": [
                    0.0,
                    0.004198018339649897,
                    0.10286536841010793,
                    0.7400119578818989,
                    0.9529993765021595,
                    0.9687373876897292,
                    0.9849126736807795,
                    0.9964842869358094,
                    1.0144257785927833
                  ],
                  "flow": "clamp"
                }
              ],
              "flow": "clamp"
            }
          },
          {
            "key": "down",
            "value": {
              "nodetype": "binning",
              "input": "abssceta",
              "edges": [
                0.0,
                0.800000011920929,
                1.4789999723434448,
                2.5
              ],
              "content": [
                {
                  "nodetype": "binning",
                  "input": "pt",
                  "edges": [
                    5.0,
                    10.0,
                    20.0,
                    23.0,
                    25.0,
                    30.0,
                    40.0,
                    50.0,
                    100.0,
                    200.0
                  ],
                  "content": [
                    0.0,
                    -1.22327612337917e-05,
                    0.0480440679714569,
                    0.7730848515255393,
                    0.9270150963651296,
                    0.951979557276688,
                    0.9497026412371459,
                    0.9654466149517006,
                    0.9822546263847769
                  ],
                  "flow": "clamp"
                },
                {
                  "nodetype": "binning",
                  "input": "pt",
                  "edges": [
                    5.0,
                    10.0,
                    20.0,
                    23.0,
                    25.0,
                    30.0,
                    40.0,
                    50.0,
                    100.0,
                    200.0
                  ],
                  "content": [
                    0.0,
                    -0.0022139115937761166,
                    0.06370009692965654,
                    0.7046231703229928,
                    0.925112391313231,
                    0.9517433569519863,
                    0.9580478058940538,
                    0.9671701356485843,
                    0.9762780063272329
                  ],
                  "flow": "clamp"
                },
                {
                  "nodetype": "binning",
                  "input": "pt",
                  "edges": [
                    5.0,
                    10.0,
                    20.0,
                    23.0,
                    25.0,
                    30.0,
                    40.0,
                    50.0,
                    100.0,
                    200.0
                  ],
                  "content": [
                    0.0,
                    0.0013631579543483558,
                    0.06932878310331081,
                    0.5166273832608352,
                    0.9081682697283971,
                    0.9505448924723188,
                    0.9619780214470822,
                    0.969251630034922,
                    0.9646243764493491
                  ],
                  "flow": "clamp"
                }
              ],
              "flow": "clamp"
            }
          }
        ],
        "default": null
      }
    }
  ],
  "compound_corrections": null
}