{
  "schema_version": 2,
  "description": "Measured efficiency for Mu8El23_El23Leg Trigger path",
  "corrections": [
    {
      "name": "Mu8El23_Data",
      "description": "",
      "version": 1,
      "inputs": [
        {
          "name": "abssceta",
          "type": "real",
          "description": "abssceta"
        },
        {
          "name": "pt",
          "type": "real",
          "description": "pt"
        },
        {
          "name": "syst",
          "type": "string",
          "description": "systematic variation (nom, up, down)"
        }
      ],
      "output": {
        "name": "eff_data",
        "type": "real",
        "description": "eff_data"
      },
      "generic_formulas": null,
      "data": {
        "nodetype": "category",
        "input": "syst",
        "content": [
          {
            "key": "nom",
            "value": {
              "nodetype": "binning",
              "input": "abssceta",
              "edges": [
                0.0,
                0.800000011920929,
                1.4789999723434448,
                2.5
              ],
              "content": [
                {
                  "nodetype": "binning",
                  "input": "pt",
                  "edges": [
                    5.0,
                    10.0,
                    20.0,
                    23.0,
                    25.0,
                    30.0,
                    40.0,
                    50.0,
                    100.0,
                    200.0
                  ],
                  "content": [
                    0.0,
                    0.0006843065693430657,
                    0.07369281045751634,
                    0.781227946365561,
                    0.9316311260755705,
                    0.9497350414158564,
                    0.961259862889665,
                    0.9758682032639802,
                    0.9852502485913158
                  ],
                  "flow": "clamp"
                },
                {
                  "nodetype": "binning",
                  "input": "pt",
                  "edges": [
                    5.0,
                    10.0,
                    20.0,
                    23.0,
                    25.0,
                    30.0,
                    40.0,
                    50.0,
                    100.0,
                    200.0
                  ],
                  "content": [
                    0.0,
                    0.0012101653892698668,
                    0.07713963963963964,
                    0.6758309396799344,
                    0.9204562972098043,
                    0.948811544991511,
                    0.9590146750524109,
                    0.9699354231706796,
                    0.9832751599767307
                  ],
                  "flow": "clamp"
                },
                {
                  "nodetype": "binning",
                  "input": "pt",
                  "edges": [
                    5.0,
                    10.0,
                    20.0,
                    23.0,
                    25.0,
                    30.0,
                    40.0,
                    50.0,
                    100.0,
                    200.0
                  ],
                  "content": [
                    0.0,
                    0.003355704697986577,
                    0.06144278606965174,
                    0.5271518285925378,
                    0.8992186254185935,
                    0.9473227206946454,
                    0.9624679357364655,
                    0.9753364672548136,
                    0.9832947828321769
                  ],
                  "flow": "clamp"
                }
              ],
              "flow": "clamp"
            }
          },
          {
            "key": "up",
            "value": {
              "nodetype": "binning",
              "input": "abssceta",
              "edges": [
                0.0,
                0.800000011920929,
                1.4789999723434448,
                2.5
              ],
              "content": [
                {
                  "nodetype": "binning",
                  "input": "pt",
                  "edges": [
                    5.0,
                    10.0,
                    20.0,
                    23.0,
                    25.0,
                    30.0,
                    40.0,
                    50.0,
                    100.0,
                    200.0
                  ],
                  "content": [
                    0.0,
                    0.0009681668873323466,
                    0.07736567945444058,
                    0.799805265400152,
                    0.9447086494954365,
                    0.9595017104212998,
                    0.9723064484286099,
                    0.9829277211633201,
                    0.9979822036583885
                  ],
                  "flow": "clamp"
                },
                {
                  "nodetype": "binning",
                  "input": "pt",
                  "edges": [
                    5.0,
                    10.0,
                    20.0,
                    23.0,
                    25.0,
                    30.0,
                    40.0,
                    50.0,
                    100.0,
                    200.0
                  ],
                  "content": [
                    0.0,
                    0.0017475932709588905,
                    0.082095896904334,
                    0.6980901436365203,
                    0.9375686936114905,
                    0.96134098168387,
                    0.9730705748497914,
                    0.9789769857454885,
                    1.0001347588637362
                  ],
                  "flow": "clamp"
                },
                {
                  "nodetype": "binning",
                  "input": "pt",
                  "edges": [
                    5.0,
                    10.0,
                    20.0,
                    23.0,
                    25.0,
                    30.0,
                    40.0,
                    50.0,
                    100.0,
                    200.0
                  ],
                  "content": [
                    0.0,
                    0.004058022750331692,
                    0.0655137193847556,
                    0.5444883728192947,
                    0.9157871879692487,
                    0.9606905735973011,
                    0.9784956060628698,
                    0.9864755639292991,
                    1.0056928038746655
                  ],
                  "flow": "clamp"
                }
              ],
              "flow": "clamp"
            }
          },
          {
            "key": "down",
            "value": {
              "nodetype": "binning",
              "input": "abssceta",
              "edges": [
                0.0,
                0.800000011920929,
                1.4789999723434448,
                2.5
              ],
              "content": [
                {
                  "nodetype": "binning",
                  "input": "pt",
                  "edges": [
                    5.0,
                    10.0,
                    20.0,
                    23.0,
                    25.0,
                    30.0,
                    40.0,
                    50.0,
                    100.0,
                    200.0
                  ],
                  "content": [
                    0.0,
                    0.0004004462513537848,
                    0.07001994146059211,
                    0.7626506273309701,
                    0.9185536026557045,
                    0.939968372410413,
                    0.9502132773507201,
                    0.9688086853646403,
                    0.9725182935242431
                  ],
                  "flow": "clamp"
                },
                {
                  "nodetype": "binning",
                  "input": "pt",
                  "edges": [
                    5.0,
                    10.0,
                    20.0,
                    23.0,
                    25.0,
                    30.0,
                    40.0,
                    50.0,
                    100.0,
                    200.0
                  ],
                  "content": [
                    0.0,
                    0.0006727375075808431,
                    0.07218338237494529,
                    0.6535717357233484,
                    0.903343900808118,
                    0.9362821082991519,
                    0.9449587752550304,
                    0.9608938605958707,
                    0.9664155610897252
                  ],
                  "flow": "clamp"
                },
                {
                  "nodetype": "binning",
                  "input": "pt",
                  "edges": [
                    5.0,
                    10.0,
                    20.0,
                    23.0,
                    25.0,
                    30.0,
                    40.0,
                    50.0,
                    100.0,
                    200.0
                  ],
                  "content": [
                    0.0,
                    0.002653386645641462,
                    0.05737185275454788,
                    0.5098152843657809,
                    0.8826500628679383,
                    0.9339548677919897,
                    0.9464402654100612,
                    0.9641973705803281,
                    0.9608967617896882
                  ],
                  "flow": "clamp"
                }
              ],
              "flow": "clamp"
            }
          }
        ],
        "default": null
      }
    },
    {
      "name": "Mu8El23_MC",
      "description": "",
      "version": 1,
      "inputs": [
        {
          "name": "abssceta",
          "type": "real",
          "description": "abssceta"
        },
        {
          "name": "pt",
          "type": "real",
          "description": "pt"
        },
        {
          "name": "syst",
          "type": "string",
          "description": "systematic variation (nom, up, down)"
        }
      ],
      "output": {
        "name": "eff_mc",
        "type": "real",
        "description": "eff_mc"
      },
      "generic_formulas": null,
      "data": {
        "nodetype": "category",
        "input": "syst",
        "content": [
          {
            "key": "nom",
            "value": {
              "nodetype": "binning",
              "input": "abssceta",
              "edges": [
                0.0,
                0.800000011920929,
                1.4789999723434448,
                2.5
              ],
              "content": [
                {
                  "nodetype": "binning",
                  "input": "pt",
                  "edges": [
                    5.0,
                    10.0,
                    20.0,
                    23.0,
                    25.0,
                    30.0,
                    40.0,
                    50.0,
                    100.0,
                    200.0
                  ],
                  "content": [
                    0.0,
                    0.0004514709476053147,
                    0.055411814277598365,
                    0.7896415321623462,
                    0.9358066581722141,
                    0.9556974453041431,
                    0.9672691256168711,
                    0.9822160022606762,
                    0.9918244193857563
                  ],
                  "flow": "clamp"
                },
                {
                  "nodetype": "binning",
                  "input": "pt",
                  "edges": [
                    5.0,
                    10.0,
                    20.0,
                    23.0,
                    25.0,
                    30.0,
                    40.0,
                    50.0,
                    100.0,
                    200.0
                  ],
                  "content": [
                    0.0,
                    0.0010201595872758673,
                    0.07618353418589445,
                    0.729014977625566,
                    0.9327281225669588,
                    0.9587079639653023,
                    0.9675143747110695,
                    0.9764373840674424,
                    0.9895897852493786
                  ],
                  "flow": "clamp"
                },
                {
                  "nodetype": "binning",
                  "input": "pt",
                  "edges": [
                    5.0,
                    10.0,
                    20.0,
                    23.0,
                    25.0,
                    30.0,
                    40.0,
                    50.0,
                    100.0,
                    200.0
                  ],
                  "content": [
                    0.0,
                    0.002362604010140225,
                    0.09111265523091222,
                    0.6329463910059743,
                    0.9279715091814272,
                    0.9574443277867595,
                    0.9700369320734047,
                    0.9818705973534634,
                    0.9890651280262389
                  ],
                  "flow": "clamp"
                }
              ],
              "flow": "clamp"
            }
          },
          {
            "key": "up",
            "value": {
              "nodetype": "binning",
              "input": "abssceta",
              "edges": [
                0.0,
                0.800000011920929,
                1.4789999723434448,
                2.5
              ],
              "content": [
                {
                  "nodetype": "binning",
                  "input": "pt",
                  "edges": [
                    5.0,
                    10.0,
                    20.0,
                    23.0,
                    25.0,
                    30.0,
                    40.0,
                    50.0,
                    100.0,
                    200.0
                  ],
                  "content": [
                    0.0,
                    0.0009067680609164911,
                    0.056329653838410355,
                    0.7961094634391387,
                    0.9429727973003862,
                    0.9595333284905542,
                    0.9714083902679228,
                    0.9888637697655787,
                    1.0300153928974158
                  ],
                  "flow": "clamp"
                },
                {
                  "nodetype": "binning",
                  "input": "pt",
                  "edges": [
                    5.0,
                    10.0,
                    20.0,
                    23.0,
                    25.0,
                    30.0,
                    40.0,
                    50.0,
                    100.0,
                    200.0
                  ],
                  "content": [
                    0.0,
                    0.002048448395083104,
                    0.07910656337170471,
                    0.7688881234855243,
                    0.9467379966838644,
                    0.9647905801999523,
                    0.9819013005761708,
                    0.98252555809434,
                    1.042226940064576
                  ],
                  "flow": "clamp"
                },
                {
                  "nodetype": "binning",
                  "input": "pt",
                  "edges": [
                    5.0,
                    10.0,
                    20.0,
                    23.0,
                    25.0,
                    30.0,
                    40.0,
                    50.0,
                    100.0,
                    200.0
                  ],
                  "content": [
                    0.0,
                    0.005040875787558324,
                    0.10415337483725803,
                    0.6392167753095727,
                    0.9410481689868065,
                    0.9608689884938604,
                    1.0091946717917408,
                    1.0088942842428974,
                    1.0247644977563646
                  ],
                  "flow": "clamp"
                }
              ],
              "flow": "clamp"
            }
          },
          {
            "key": "down",
            "value": {
              "nodetype": "binning",
              "input": "abssceta",
              "edges": [
                0.0,
                0.800000011920929,
                1.4789999723434448,
                2.5
              ],
              "content": [
                {
                  "nodetype": "binning",
                  "input": "pt",
                  "edges": [
                    5.0,
                    10.0,
                    20.0,
                    23.0,
                    25.0,
                    30.0,
                    40.0,
                    50.0,
                    100.0,
                    200.0
                  ],
                  "content": [
                    0.0,
                    -3.826165705861698e-06,
                    0.054493974716786374,
                    0.7831736008855538,
                    0.928640519044042,
                    0.9518615621177321,
                    0.9631298609658193,
                    0.9755682347557737,
                    0.9536334458740968
                  ],
                  "flow": "clamp"
                },
                {
                  "nodetype": "binning",
                  "input": "pt",
                  "edges": [
                    5.0,
                    10.0,
                    20.0,
                    23.0,
                    25.0,
                    30.0,
                    40.0,
                    50.0,
                    100.0,
                    200.0
                  ],
                  "content": [
                    0.0,
                    -8.129220531369373e-06,
                    0.07326050500008419,
                    0.6891418317656077,
                    0.9187182484500532,
                    0.9526253477306523,
                    0.9531274488459682,
                    0.9703492100405449,
                    0.9369526304341811
                  ],
                  "flow": "clamp"
                },
                {
                  "nodetype": "binning",
                  "input": "pt",
                  "edges": [
                    5.0,
                    10.0,
                    20.0,
                    23.0,
                    25.0,
                    30.0,
                    40.0,
                    50.0,
                    100.0,
                    200.0
                  ],
                  "content": [
                    0.0,
                    -0.0003156677672778744,
                    0.07807193562456641,
                    0.6266760067023759,
                    0.9148948493760479,
                    0.9540196670796586,
                    0.9308791923550684,
                    0.9548469104640294,
                    0.9533657582961134
                  ],
                  "flow": "clamp"
                }
              ],
              "flow": "clamp"
            }
          }
        ],
        "default": null
      }
    }
  ],
  "compound_corrections": null
}